{"api_version": "2023-07-31", "model_id": "prebuilt-document", "content": "AIVEPET, S.R.L - REP. DOMINICANA Reporte Fotogr\u00e1fico Ref. AIVEPET: 2023 02 077 Fecha de Inspecci\u00f3n: 15/02/2023 E/S SOL PETR\u00d3LEO SAN LUIS - CARRETERA PRIMERO DE MAYO SAN LUIS, SANTO DOMINGO\naivepet\nSOL PETROLEO\nVISTA PANOR\u00c1MICA DE LA ESTACI\u00d3N DE SERVICIO\nPROCESO DE MUESTREO DE LOS TANQUES DE ALMACENAMIENTO\nPROCESO DE MUESTREO DE LOS TANQUES DE ALMACENAMIENTO\nMEDICI\u00d3N DEL CORTE DE AGUA LIBRE EN LOS TANQUES DE ALMACENAMIENTO\n--\nMEDICI\u00d3N DEL CORTE DE AGUA LIBRE EN LOS TANQUES DE ALMACENAMIENTO\nMUESTRAS TOMADAS DURANTE DE LA INSPECCI\u00d3N", "languages": [], "pages": [{"page_number": 1, "angle": 0.09362047165632248, "width": 8.5, "height": 11.0, "unit": "inch", "lines": [{"content": "AIVEPET, S.R.L - REP. DOMINICANA", "polygon": [{"x": 2.7697, "y": 0.2244}, {"x": 5.6921, "y": 0.2292}, {"x": 5.6921, "y": 0.4058}, {"x": 2.7697, "y": 0.401}], "spans": [{"offset": 0, "length": 32}]}, {"content": "Reporte Fotogr\u00e1fico", "polygon": [{"x": 3.3666, "y": 0.4297}, {"x": 5.0761, "y": 0.4345}, {"x": 5.0761, "y": 0.6254}, {"x": 3.3666, "y": 0.6207}], "spans": [{"offset": 33, "length": 19}]}, {"content": "Ref. AIVEPET: 2023 02 077", "polygon": [{"x": 3.2806, "y": 0.6875}, {"x": 5.1573, "y": 0.6923}, {"x": 5.1573, "y": 0.8498}, {"x": 3.2806, "y": 0.8451}], "spans": [{"offset": 53, "length": 25}]}, {"content": "Fecha de Inspecci\u00f3n: 15/02/2023", "polygon": [{"x": 3.0753, "y": 0.8737}, {"x": 5.3626, "y": 0.8737}, {"x": 5.3626, "y": 1.0313}, {"x": 3.0753, "y": 1.0313}], "spans": [{"offset": 79, "length": 31}]}, {"content": "E/S SOL PETR\u00d3LEO SAN LUIS - CARRETERA PRIMERO DE MAYO SAN LUIS, SANTO DOMINGO", "polygon": [{"x": 0.7879, "y": 1.0169}, {"x": 7.65, "y": 1.0503}, {"x": 7.65, "y": 1.2222}, {"x": 0.7879, "y": 1.1888}], "spans": [{"offset": 111, "length": 77}]}, {"content": "aivepet", "polygon": [{"x": 0.4393, "y": 0.7973}, {"x": 0.9933, "y": 0.7973}, {"x": 0.9933, "y": 0.9214}, {"x": 0.4393, "y": 0.9262}], "spans": [{"offset": 189, "length": 7}]}, {"content": "SOL", "polygon": [{"x": 2.9607, "y": 2.2248}, {"x": 3.2281, "y": 2.1819}, {"x": 3.2424, "y": 2.2917}, {"x": 2.975, "y": 2.3251}], "spans": [{"offset": 197, "length": 3}]}, {"content": "PETROLEO", "polygon": [{"x": 2.9702, "y": 2.3251}, {"x": 3.2758, "y": 2.2917}, {"x": 3.2854, "y": 2.3442}, {"x": 2.975, "y": 2.3824}], "spans": [{"offset": 201, "length": 8}]}, {"content": "VISTA PANOR\u00c1MICA DE LA ESTACI\u00d3N DE", "polygon": [{"x": 0.85, "y": 3.9054}, {"x": 3.6101, "y": 3.9054}, {"x": 3.6101, "y": 4.082}, {"x": 0.85, "y": 4.0725}], "spans": [{"offset": 210, "length": 34}]}, {"content": "SERVICIO", "polygon": [{"x": 1.9149, "y": 4.0868}, {"x": 2.5739, "y": 4.0868}, {"x": 2.5739, "y": 4.2205}, {"x": 1.9149, "y": 4.2205}], "spans": [{"offset": 245, "length": 8}]}, {"content": "PROCESO DE MUESTREO DE LOS TANQUES DE", "polygon": [{"x": 4.6511, "y": 4.0056}, {"x": 7.7933, "y": 4.0104}, {"x": 7.7933, "y": 4.1536}, {"x": 4.6511, "y": 4.1441}], "spans": [{"offset": 254, "length": 37}]}, {"content": "ALMACENAMIENTO", "polygon": [{"x": 5.5728, "y": 4.1727}, {"x": 6.8669, "y": 4.1727}, {"x": 6.8669, "y": 4.3016}, {"x": 5.5728, "y": 4.3016}], "spans": [{"offset": 292, "length": 14}]}, {"content": "PROCESO DE MUESTREO DE LOS TANQUES DE", "polygon": [{"x": 0.5874, "y": 7.0994}, {"x": 3.7247, "y": 7.1089}, {"x": 3.7247, "y": 7.2426}, {"x": 0.5874, "y": 7.2331}], "spans": [{"offset": 307, "length": 37}]}, {"content": "ALMACENAMIENTO", "polygon": [{"x": 1.509, "y": 7.2665}, {"x": 2.7983, "y": 7.2665}, {"x": 2.7983, "y": 7.4002}, {"x": 1.509, "y": 7.3954}], "spans": [{"offset": 345, "length": 14}]}, {"content": "MEDICI\u00d3N DEL CORTE DE AGUA LIBRE EN LOS", "polygon": [{"x": 4.6511, "y": 7.066}, {"x": 7.7646, "y": 7.0755}, {"x": 7.7646, "y": 7.2235}, {"x": 4.6511, "y": 7.2188}], "spans": [{"offset": 360, "length": 39}]}, {"content": "TANQUES DE ALMACENAMIENTO", "polygon": [{"x": 5.1143, "y": 7.2426}, {"x": 7.3062, "y": 7.2426}, {"x": 7.3062, "y": 7.3811}, {"x": 5.1143, "y": 7.3811}], "spans": [{"offset": 400, "length": 25}]}, {"content": "--", "polygon": [{"x": 7.7455, "y": 8.8181}, {"x": 7.8553, "y": 8.8086}, {"x": 7.8553, "y": 8.8468}, {"x": 7.7455, "y": 8.8563}], "spans": [{"offset": 426, "length": 2}]}, {"content": "MEDICI\u00d3N DEL CORTE DE AGUA LIBRE EN LOS", "polygon": [{"x": 0.6447, "y": 10.2027}, {"x": 3.7629, "y": 10.217}, {"x": 3.7629, "y": 10.3841}, {"x": 0.6447, "y": 10.365}], "spans": [{"offset": 429, "length": 39}]}, {"content": "TANQUES DE ALMACENAMIENTO", "polygon": [{"x": 1.1174, "y": 10.3793}, {"x": 3.3093, "y": 10.3937}, {"x": 3.3093, "y": 10.5273}, {"x": 1.1174, "y": 10.513}], "spans": [{"offset": 469, "length": 25}]}, {"content": "MUESTRAS TOMADAS DURANTE DE LA", "polygon": [{"x": 5.0522, "y": 10.2218}, {"x": 7.6452, "y": 10.2218}, {"x": 7.6452, "y": 10.3602}, {"x": 5.0522, "y": 10.3602}], "spans": [{"offset": 495, "length": 30}]}, {"content": "INSPECCI\u00d3N", "polygon": [{"x": 5.9166, "y": 10.3746}, {"x": 6.7761, "y": 10.3746}, {"x": 6.7761, "y": 10.513}, {"x": 5.9166, "y": 10.513}], "spans": [{"offset": 526, "length": 10}]}], "words": [{"content": "AIVEPET,", "polygon": [{"x": 2.7792, "y": 0.2292}, {"x": 3.5433, "y": 0.2292}, {"x": 3.5433, "y": 0.4058}, {"x": 2.784, "y": 0.401}], "span": {"offset": 0, "length": 8}, "confidence": 0.976}, {"content": "S.R.L", "polygon": [{"x": 3.5767, "y": 0.2292}, {"x": 3.9826, "y": 0.2292}, {"x": 3.9826, "y": 0.4058}, {"x": 3.5767, "y": 0.4058}], "span": {"offset": 9, "length": 5}, "confidence": 0.993}, {"content": "-", "polygon": [{"x": 4.0303, "y": 0.2292}, {"x": 4.1211, "y": 0.2292}, {"x": 4.1211, "y": 0.4058}, {"x": 4.0256, "y": 0.4058}], "span": {"offset": 15, "length": 1}, "confidence": 0.995}, {"content": "REP.", "polygon": [{"x": 4.1688, "y": 0.2292}, {"x": 4.5604, "y": 0.2292}, {"x": 4.5604, "y": 0.4058}, {"x": 4.164, "y": 0.4058}], "span": {"offset": 17, "length": 4}, "confidence": 0.986}, {"content": "DOMINICANA", "polygon": [{"x": 4.5938, "y": 0.2292}, {"x": 5.6492, "y": 0.2339}, {"x": 5.6444, "y": 0.4058}, {"x": 4.5938, "y": 0.4058}], "span": {"offset": 22, "length": 10}, "confidence": 0.991}, {"content": "Reporte", "polygon": [{"x": 3.3713, "y": 0.4345}, {"x": 4.0351, "y": 0.4345}, {"x": 4.0399, "y": 0.6254}, {"x": 3.3713, "y": 0.6207}], "span": {"offset": 33, "length": 7}, "confidence": 0.994}, {"content": "Fotogr\u00e1fico", "polygon": [{"x": 4.0876, "y": 0.4345}, {"x": 5.0666, "y": 0.4392}, {"x": 5.0713, "y": 0.6254}, {"x": 4.0876, "y": 0.6254}], "span": {"offset": 41, "length": 11}, "confidence": 0.981}, {"content": "Ref.", "polygon": [{"x": 3.2854, "y": 0.697}, {"x": 3.5815, "y": 0.6923}, {"x": 3.5815, "y": 0.8451}, {"x": 3.2854, "y": 0.8451}], "span": {"offset": 53, "length": 4}, "confidence": 0.991}, {"content": "AIVEPET:", "polygon": [{"x": 3.6101, "y": 0.6923}, {"x": 4.3169, "y": 0.6923}, {"x": 4.3121, "y": 0.8498}, {"x": 3.6101, "y": 0.8451}], "span": {"offset": 58, "length": 8}, "confidence": 0.993}, {"content": "2023", "polygon": [{"x": 4.3455, "y": 0.6923}, {"x": 4.675, "y": 0.697}, {"x": 4.675, "y": 0.8498}, {"x": 4.3407, "y": 0.8498}], "span": {"offset": 67, "length": 4}, "confidence": 0.982}, {"content": "02", "polygon": [{"x": 4.7037, "y": 0.697}, {"x": 4.8756, "y": 0.697}, {"x": 4.8756, "y": 0.8498}, {"x": 4.7037, "y": 0.8498}], "span": {"offset": 72, "length": 2}, "confidence": 0.995}, {"content": "077", "polygon": [{"x": 4.909, "y": 0.697}, {"x": 5.1621, "y": 0.7018}, {"x": 5.1573, "y": 0.8451}, {"x": 4.9042, "y": 0.8498}], "span": {"offset": 75, "length": 3}, "confidence": 0.995}, {"content": "Fecha", "polygon": [{"x": 3.0753, "y": 0.8785}, {"x": 3.4955, "y": 0.8785}, {"x": 3.5003, "y": 1.036}, {"x": 3.0801, "y": 1.0313}], "span": {"offset": 79, "length": 5}, "confidence": 0.995}, {"content": "de", "polygon": [{"x": 3.5385, "y": 0.8785}, {"x": 3.7056, "y": 0.8785}, {"x": 3.7104, "y": 1.036}, {"x": 3.5385, "y": 1.036}], "span": {"offset": 85, "length": 2}, "confidence": 0.995}, {"content": "Inspecci\u00f3n:", "polygon": [{"x": 3.7486, "y": 0.8785}, {"x": 4.6034, "y": 0.8785}, {"x": 4.6034, "y": 1.0313}, {"x": 3.7486, "y": 1.036}], "span": {"offset": 88, "length": 11}, "confidence": 0.87}, {"content": "15/02/2023", "polygon": [{"x": 4.632, "y": 0.8785}, {"x": 5.3579, "y": 0.8832}, {"x": 5.3579, "y": 1.0265}, {"x": 4.632, "y": 1.0313}], "span": {"offset": 100, "length": 10}, "confidence": 0.983}, {"content": "E/S", "polygon": [{"x": 0.7927, "y": 1.0217}, {"x": 1.0171, "y": 1.0217}, {"x": 1.0171, "y": 1.1984}, {"x": 0.7975, "y": 1.1936}], "span": {"offset": 111, "length": 3}, "confidence": 0.995}, {"content": "SOL", "polygon": [{"x": 1.0697, "y": 1.0217}, {"x": 1.3562, "y": 1.0265}, {"x": 1.361, "y": 1.1984}, {"x": 1.0697, "y": 1.1984}], "span": {"offset": 115, "length": 3}, "confidence": 0.995}, {"content": "PETR\u00d3LEO", "polygon": [{"x": 1.4135, "y": 1.0265}, {"x": 2.2062, "y": 1.036}, {"x": 2.211, "y": 1.1984}, {"x": 1.4135, "y": 1.1984}], "span": {"offset": 119, "length": 8}, "confidence": 0.993}, {"content": "SAN", "polygon": [{"x": 2.2826, "y": 1.036}, {"x": 2.55, "y": 1.036}, {"x": 2.55, "y": 1.2031}, {"x": 2.2826, "y": 1.2031}], "span": {"offset": 128, "length": 3}, "confidence": 0.995}, {"content": "LUIS", "polygon": [{"x": 2.6264, "y": 1.036}, {"x": 2.9559, "y": 1.0408}, {"x": 2.9607, "y": 1.2031}, {"x": 2.6264, "y": 1.2031}], "span": {"offset": 132, "length": 4}, "confidence": 0.982}, {"content": "-", "polygon": [{"x": 2.9893, "y": 1.0408}, {"x": 3.0848, "y": 1.0408}, {"x": 3.0896, "y": 1.2031}, {"x": 2.9941, "y": 1.2031}], "span": {"offset": 137, "length": 1}, "confidence": 0.946}, {"content": "CARRETERA", "polygon": [{"x": 3.1278, "y": 1.0408}, {"x": 4.0399, "y": 1.0456}, {"x": 4.0447, "y": 1.2079}, {"x": 3.1326, "y": 1.2031}], "span": {"offset": 139, "length": 9}, "confidence": 0.991}, {"content": "PRIMERO", "polygon": [{"x": 4.1067, "y": 1.0503}, {"x": 4.7705, "y": 1.0503}, {"x": 4.7753, "y": 1.2127}, {"x": 4.1067, "y": 1.2079}], "span": {"offset": 149, "length": 7}, "confidence": 0.992}, {"content": "DE", "polygon": [{"x": 4.8326, "y": 1.0503}, {"x": 5.0379, "y": 1.0503}, {"x": 5.0427, "y": 1.2127}, {"x": 4.8374, "y": 1.2127}], "span": {"offset": 157, "length": 2}, "confidence": 0.941}, {"content": "MAYO", "polygon": [{"x": 5.0809, "y": 1.0551}, {"x": 5.5107, "y": 1.0551}, {"x": 5.5154, "y": 1.2127}, {"x": 5.0857, "y": 1.2127}], "span": {"offset": 160, "length": 4}, "confidence": 0.99}, {"content": "SAN", "polygon": [{"x": 5.5871, "y": 1.0551}, {"x": 5.8545, "y": 1.0551}, {"x": 5.8545, "y": 1.2127}, {"x": 5.5871, "y": 1.2127}], "span": {"offset": 165, "length": 3}, "confidence": 0.995}, {"content": "LUIS,", "polygon": [{"x": 5.9309, "y": 1.0551}, {"x": 6.3272, "y": 1.0551}, {"x": 6.3272, "y": 1.2174}, {"x": 5.9309, "y": 1.2174}], "span": {"offset": 169, "length": 5}, "confidence": 0.987}, {"content": "SANTO", "polygon": [{"x": 6.3559, "y": 1.0551}, {"x": 6.843, "y": 1.0551}, {"x": 6.843, "y": 1.2174}, {"x": 6.3607, "y": 1.2174}], "span": {"offset": 175, "length": 5}, "confidence": 0.995}, {"content": "DOMINGO", "polygon": [{"x": 6.9146, "y": 1.0551}, {"x": 7.6118, "y": 1.0599}, {"x": 7.6166, "y": 1.2222}, {"x": 6.9194, "y": 1.2174}], "span": {"offset": 181, "length": 7}, "confidence": 0.993}, {"content": "aivepet", "polygon": [{"x": 0.4489, "y": 0.8021}, {"x": 0.9933, "y": 0.7973}, {"x": 0.9933, "y": 0.9262}, {"x": 0.4489, "y": 0.9262}], "span": {"offset": 189, "length": 7}, "confidence": 0.989}, {"content": "SOL", "polygon": [{"x": 2.9798, "y": 2.2105}, {"x": 3.2233, "y": 2.1819}, {"x": 3.2376, "y": 2.2917}, {"x": 2.9941, "y": 2.3251}], "span": {"offset": 197, "length": 3}, "confidence": 0.86}, {"content": "PETROLEO", "polygon": [{"x": 2.9702, "y": 2.3299}, {"x": 3.2711, "y": 2.2917}, {"x": 3.2758, "y": 2.349}, {"x": 2.9798, "y": 2.3824}], "span": {"offset": 201, "length": 8}, "confidence": 0.552}, {"content": "VISTA", "polygon": [{"x": 0.8691, "y": 3.9102}, {"x": 1.2607, "y": 3.9102}, {"x": 1.2559, "y": 4.0725}, {"x": 0.8643, "y": 4.0725}], "span": {"offset": 210, "length": 5}, "confidence": 0.989}, {"content": "PANOR\u00c1MICA", "polygon": [{"x": 1.2941, "y": 3.9102}, {"x": 2.211, "y": 3.9054}, {"x": 2.2062, "y": 4.0773}, {"x": 1.2893, "y": 4.0725}], "span": {"offset": 216, "length": 10}, "confidence": 0.961}, {"content": "DE", "polygon": [{"x": 2.2539, "y": 3.9054}, {"x": 2.4354, "y": 3.9054}, {"x": 2.4306, "y": 4.0773}, {"x": 2.2492, "y": 4.0773}], "span": {"offset": 227, "length": 2}, "confidence": 0.994}, {"content": "LA", "polygon": [{"x": 2.4688, "y": 3.9054}, {"x": 2.6598, "y": 3.9054}, {"x": 2.6551, "y": 4.082}, {"x": 2.464, "y": 4.0773}], "span": {"offset": 230, "length": 2}, "confidence": 0.983}, {"content": "ESTACI\u00d3N", "polygon": [{"x": 2.6933, "y": 3.9054}, {"x": 3.3618, "y": 3.9102}, {"x": 3.3618, "y": 4.0868}, {"x": 2.6885, "y": 4.082}], "span": {"offset": 233, "length": 8}, "confidence": 0.995}, {"content": "DE", "polygon": [{"x": 3.4048, "y": 3.9102}, {"x": 3.5958, "y": 3.9149}, {"x": 3.5958, "y": 4.0868}, {"x": 3.4048, "y": 4.0868}], "span": {"offset": 242, "length": 2}, "confidence": 0.939}, {"content": "SERVICIO", "polygon": [{"x": 1.934, "y": 4.0916}, {"x": 2.5357, "y": 4.0916}, {"x": 2.5357, "y": 4.2253}, {"x": 1.934, "y": 4.2205}], "span": {"offset": 245, "length": 8}, "confidence": 0.993}, {"content": "PROCESO", "polygon": [{"x": 4.6607, "y": 4.0104}, {"x": 5.291, "y": 4.0104}, {"x": 5.291, "y": 4.1489}, {"x": 4.6607, "y": 4.1489}], "span": {"offset": 254, "length": 7}, "confidence": 0.993}, {"content": "DE", "polygon": [{"x": 5.3531, "y": 4.0104}, {"x": 5.525, "y": 4.0104}, {"x": 5.525, "y": 4.1489}, {"x": 5.3531, "y": 4.1489}], "span": {"offset": 262, "length": 2}, "confidence": 0.941}, {"content": "MUESTREO", "polygon": [{"x": 5.568, "y": 4.0104}, {"x": 6.3081, "y": 4.0152}, {"x": 6.3081, "y": 4.1489}, {"x": 5.5728, "y": 4.1489}], "span": {"offset": 265, "length": 8}, "confidence": 0.995}, {"content": "DE", "polygon": [{"x": 6.3702, "y": 4.0152}, {"x": 6.5421, "y": 4.0152}, {"x": 6.5421, "y": 4.1489}, {"x": 6.3702, "y": 4.1489}], "span": {"offset": 274, "length": 2}, "confidence": 0.995}, {"content": "LOS", "polygon": [{"x": 6.5994, "y": 4.0152}, {"x": 6.8573, "y": 4.0152}, {"x": 6.8573, "y": 4.1536}, {"x": 6.5947, "y": 4.1489}], "span": {"offset": 277, "length": 3}, "confidence": 0.995}, {"content": "TANQUES", "polygon": [{"x": 6.9242, "y": 4.0152}, {"x": 7.5449, "y": 4.0152}, {"x": 7.5402, "y": 4.1536}, {"x": 6.9194, "y": 4.1536}], "span": {"offset": 281, "length": 7}, "confidence": 0.994}, {"content": "DE", "polygon": [{"x": 7.5879, "y": 4.02}, {"x": 7.7598, "y": 4.02}, {"x": 7.7598, "y": 4.1536}, {"x": 7.5879, "y": 4.1536}], "span": {"offset": 289, "length": 2}, "confidence": 0.994}, {"content": "ALMACENAMIENTO", "polygon": [{"x": 5.5871, "y": 4.1775}, {"x": 6.8287, "y": 4.1775}, {"x": 6.8334, "y": 4.3064}, {"x": 5.5919, "y": 4.3064}], "span": {"offset": 292, "length": 14}, "confidence": 0.989}, {"content": "PROCESO", "polygon": [{"x": 0.5921, "y": 7.0994}, {"x": 1.2272, "y": 7.1042}, {"x": 1.2272, "y": 7.2378}, {"x": 0.5921, "y": 7.2331}], "span": {"offset": 307, "length": 7}, "confidence": 0.995}, {"content": "DE", "polygon": [{"x": 1.2989, "y": 7.1042}, {"x": 1.466, "y": 7.1042}, {"x": 1.4708, "y": 7.2378}, {"x": 1.2989, "y": 7.2378}], "span": {"offset": 315, "length": 2}, "confidence": 0.991}, {"content": "MUESTREO", "polygon": [{"x": 1.5042, "y": 7.1042}, {"x": 2.2444, "y": 7.1042}, {"x": 2.2492, "y": 7.2426}, {"x": 1.5042, "y": 7.2378}], "span": {"offset": 318, "length": 8}, "confidence": 0.99}, {"content": "DE", "polygon": [{"x": 2.3065, "y": 7.1042}, {"x": 2.4784, "y": 7.1042}, {"x": 2.4784, "y": 7.2426}, {"x": 2.3112, "y": 7.2426}], "span": {"offset": 327, "length": 2}, "confidence": 0.995}, {"content": "LOS", "polygon": [{"x": 2.5309, "y": 7.1042}, {"x": 2.8031, "y": 7.1089}, {"x": 2.8031, "y": 7.2474}, {"x": 2.5357, "y": 7.2426}], "span": {"offset": 330, "length": 3}, "confidence": 0.961}, {"content": "TANQUES", "polygon": [{"x": 2.8556, "y": 7.1089}, {"x": 3.4812, "y": 7.1089}, {"x": 3.4812, "y": 7.2474}, {"x": 2.8556, "y": 7.2474}], "span": {"offset": 334, "length": 7}, "confidence": 0.994}, {"content": "DE", "polygon": [{"x": 3.5337, "y": 7.1089}, {"x": 3.7056, "y": 7.1089}, {"x": 3.7056, "y": 7.2474}, {"x": 3.5337, "y": 7.2474}], "span": {"offset": 342, "length": 2}, "confidence": 0.995}, {"content": "ALMACENAMIENTO", "polygon": [{"x": 1.5185, "y": 7.2713}, {"x": 2.7601, "y": 7.2665}, {"x": 2.7601, "y": 7.4049}, {"x": 1.5233, "y": 7.3954}], "span": {"offset": 345, "length": 14}, "confidence": 0.965}, {"content": "MEDICI\u00d3N", "polygon": [{"x": 4.6511, "y": 7.066}, {"x": 5.3006, "y": 7.0707}, {"x": 5.3006, "y": 7.2235}, {"x": 4.6559, "y": 7.2235}], "span": {"offset": 360, "length": 8}, "confidence": 0.948}, {"content": "DEL", "polygon": [{"x": 5.3674, "y": 7.0707}, {"x": 5.6253, "y": 7.0707}, {"x": 5.6301, "y": 7.2235}, {"x": 5.3674, "y": 7.2235}], "span": {"offset": 369, "length": 3}, "confidence": 0.995}, {"content": "CORTE", "polygon": [{"x": 5.673, "y": 7.0707}, {"x": 6.1219, "y": 7.0755}, {"x": 6.1267, "y": 7.2235}, {"x": 5.6778, "y": 7.2235}], "span": {"offset": 373, "length": 5}, "confidence": 0.993}, {"content": "DE", "polygon": [{"x": 6.1697, "y": 7.0755}, {"x": 6.3511, "y": 7.0755}, {"x": 6.3559, "y": 7.2235}, {"x": 6.1744, "y": 7.2235}], "span": {"offset": 379, "length": 2}, "confidence": 0.994}, {"content": "AGUA", "polygon": [{"x": 6.3989, "y": 7.0803}, {"x": 6.7618, "y": 7.0803}, {"x": 6.7666, "y": 7.2235}, {"x": 6.4037, "y": 7.2235}], "span": {"offset": 382, "length": 4}, "confidence": 0.988}, {"content": "LIBRE", "polygon": [{"x": 6.8191, "y": 7.0803}, {"x": 7.2154, "y": 7.0851}, {"x": 7.2154, "y": 7.2235}, {"x": 6.8239, "y": 7.2235}], "span": {"offset": 387, "length": 5}, "confidence": 0.993}, {"content": "EN", "polygon": [{"x": 7.2632, "y": 7.0851}, {"x": 7.4256, "y": 7.0851}, {"x": 7.4256, "y": 7.2235}, {"x": 7.2632, "y": 7.2235}], "span": {"offset": 393, "length": 2}, "confidence": 0.961}, {"content": "LOS", "polygon": [{"x": 7.4733, "y": 7.0898}, {"x": 7.7503, "y": 7.0898}, {"x": 7.7503, "y": 7.2188}, {"x": 7.4733, "y": 7.2235}], "span": {"offset": 396, "length": 3}, "confidence": 0.995}, {"content": "TANQUES", "polygon": [{"x": 5.1287, "y": 7.2522}, {"x": 5.7542, "y": 7.2474}, {"x": 5.759, "y": 7.3859}, {"x": 5.1334, "y": 7.3811}], "span": {"offset": 400, "length": 7}, "confidence": 0.994}, {"content": "DE", "polygon": [{"x": 5.8067, "y": 7.2474}, {"x": 5.9787, "y": 7.2474}, {"x": 5.9787, "y": 7.3859}, {"x": 5.8115, "y": 7.3859}], "span": {"offset": 408, "length": 2}, "confidence": 0.996}, {"content": "ALMACENAMIENTO", "polygon": [{"x": 6.0312, "y": 7.2474}, {"x": 7.2775, "y": 7.2474}, {"x": 7.2823, "y": 7.3811}, {"x": 6.0312, "y": 7.3859}], "span": {"offset": 411, "length": 14}, "confidence": 0.98}, {"content": "--", "polygon": [{"x": 7.7455, "y": 8.8181}, {"x": 7.8315, "y": 8.8086}, {"x": 7.8362, "y": 8.8468}, {"x": 7.7503, "y": 8.8563}], "span": {"offset": 426, "length": 2}, "confidence": 0.61}, {"content": "MEDICI\u00d3N", "polygon": [{"x": 0.6494, "y": 10.2075}, {"x": 1.3084, "y": 10.2075}, {"x": 1.3084, "y": 10.3746}, {"x": 0.6447, "y": 10.3698}], "span": {"offset": 429, "length": 8}, "confidence": 0.954}, {"content": "DEL", "polygon": [{"x": 1.3657, "y": 10.2075}, {"x": 1.6379, "y": 10.2075}, {"x": 1.6331, "y": 10.3746}, {"x": 1.361, "y": 10.3746}], "span": {"offset": 438, "length": 3}, "confidence": 0.995}, {"content": "CORTE", "polygon": [{"x": 1.6713, "y": 10.2075}, {"x": 2.1393, "y": 10.2122}, {"x": 2.1346, "y": 10.3793}, {"x": 1.6666, "y": 10.3746}], "span": {"offset": 442, "length": 5}, "confidence": 0.993}, {"content": "DE", "polygon": [{"x": 2.1728, "y": 10.2122}, {"x": 2.3542, "y": 10.2122}, {"x": 2.3542, "y": 10.3793}, {"x": 2.168, "y": 10.3793}], "span": {"offset": 448, "length": 2}, "confidence": 0.995}, {"content": "AGUA", "polygon": [{"x": 2.402, "y": 10.2122}, {"x": 2.7792, "y": 10.217}, {"x": 2.7792, "y": 10.3841}, {"x": 2.3972, "y": 10.3793}], "span": {"offset": 451, "length": 4}, "confidence": 0.983}, {"content": "LIBRE", "polygon": [{"x": 2.8222, "y": 10.217}, {"x": 3.2281, "y": 10.217}, {"x": 3.2281, "y": 10.3841}, {"x": 2.8222, "y": 10.3841}], "span": {"offset": 456, "length": 5}, "confidence": 0.976}, {"content": "EN", "polygon": [{"x": 3.2615, "y": 10.217}, {"x": 3.4334, "y": 10.2218}, {"x": 3.4334, "y": 10.3841}, {"x": 3.2615, "y": 10.3841}], "span": {"offset": 462, "length": 2}, "confidence": 0.995}, {"content": "LOS", "polygon": [{"x": 3.4764, "y": 10.2218}, {"x": 3.7629, "y": 10.2218}, {"x": 3.7629, "y": 10.3841}, {"x": 3.4764, "y": 10.3841}], "span": {"offset": 465, "length": 3}, "confidence": 0.995}, {"content": "TANQUES", "polygon": [{"x": 1.1317, "y": 10.3841}, {"x": 1.7573, "y": 10.3841}, {"x": 1.7573, "y": 10.5226}, {"x": 1.1317, "y": 10.5178}], "span": {"offset": 469, "length": 7}, "confidence": 0.993}, {"content": "DE", "polygon": [{"x": 1.8098, "y": 10.3841}, {"x": 1.977, "y": 10.3889}, {"x": 1.977, "y": 10.5226}, {"x": 1.8098, "y": 10.5226}], "span": {"offset": 477, "length": 2}, "confidence": 0.995}, {"content": "ALMACENAMIENTO", "polygon": [{"x": 2.0343, "y": 10.3889}, {"x": 3.2806, "y": 10.3984}, {"x": 3.2806, "y": 10.5273}, {"x": 2.0343, "y": 10.5226}], "span": {"offset": 480, "length": 14}, "confidence": 0.982}, {"content": "MUESTRAS", "polygon": [{"x": 5.0522, "y": 10.2313}, {"x": 5.7924, "y": 10.2266}, {"x": 5.7924, "y": 10.3602}, {"x": 5.057, "y": 10.3602}], "span": {"offset": 495, "length": 8}, "confidence": 0.993}, {"content": "TOMADAS", "polygon": [{"x": 5.8545, "y": 10.2266}, {"x": 6.4896, "y": 10.2266}, {"x": 6.4896, "y": 10.365}, {"x": 5.8593, "y": 10.3602}], "span": {"offset": 504, "length": 7}, "confidence": 0.993}, {"content": "DURANTE", "polygon": [{"x": 6.5517, "y": 10.2266}, {"x": 7.1868, "y": 10.2266}, {"x": 7.1868, "y": 10.365}, {"x": 6.5517, "y": 10.365}], "span": {"offset": 512, "length": 7}, "confidence": 0.995}, {"content": "DE", "polygon": [{"x": 7.2393, "y": 10.2266}, {"x": 7.4112, "y": 10.2266}, {"x": 7.4112, "y": 10.365}, {"x": 7.2393, "y": 10.365}], "span": {"offset": 520, "length": 2}, "confidence": 0.995}, {"content": "LA", "polygon": [{"x": 7.4542, "y": 10.2266}, {"x": 7.6261, "y": 10.2266}, {"x": 7.6261, "y": 10.365}, {"x": 7.4542, "y": 10.365}], "span": {"offset": 523, "length": 2}, "confidence": 0.992}, {"content": "INSPECCI\u00d3N", "polygon": [{"x": 5.9213, "y": 10.3793}, {"x": 6.7379, "y": 10.3746}, {"x": 6.7379, "y": 10.5178}, {"x": 5.9261, "y": 10.513}], "span": {"offset": 526, "length": 10}, "confidence": 0.982}], "selection_marks": [], "spans": [{"offset": 0, "length": 536}], "barcodes": [], "formulas": []}], "paragraphs": [{"role": null, "content": "AIVEPET, S.R.L - REP. DOMINICANA Reporte Fotogr\u00e1fico Ref. AIVEPET: 2023 02 077 Fecha de Inspecci\u00f3n: 15/02/2023 E/S SOL PETR\u00d3LEO SAN LUIS - CARRETERA PRIMERO DE MAYO SAN LUIS, SANTO DOMINGO", "bounding_regions": [{"page_number": 1, "polygon": [{"x": 0.7919, "y": 0.2053}, {"x": 7.6548, "y": 0.2387}, {"x": 7.65, "y": 1.2222}, {"x": 0.7871, "y": 1.1888}]}], "spans": [{"offset": 0, "length": 188}]}, {"role": null, "content": "aivepet", "bounding_regions": [{"page_number": 1, "polygon": [{"x": 0.4393, "y": 0.7973}, {"x": 0.9933, "y": 0.7973}, {"x": 0.9933, "y": 0.9262}, {"x": 0.4393, "y": 0.9262}]}], "spans": [{"offset": 189, "length": 7}]}, {"role": null, "content": "SOL PETROLEO", "bounding_regions": [{"page_number": 1, "polygon": [{"x": 2.9544, "y": 2.2155}, {"x": 3.2648, "y": 2.1773}, {"x": 3.2854, "y": 2.3442}, {"x": 2.975, "y": 2.3824}]}], "spans": [{"offset": 197, "length": 12}]}, {"role": null, "content": "VISTA PANOR\u00c1MICA DE LA ESTACI\u00d3N DE SERVICIO", "bounding_regions": [{"page_number": 1, "polygon": [{"x": 0.85, "y": 3.9054}, {"x": 3.6101, "y": 3.9054}, {"x": 3.6101, "y": 4.2205}, {"x": 0.85, "y": 4.2205}]}], "spans": [{"offset": 210, "length": 43}]}, {"role": null, "content": "PROCESO DE MUESTREO DE LOS TANQUES DE ALMACENAMIENTO", "bounding_regions": [{"page_number": 1, "polygon": [{"x": 4.6511, "y": 4.0056}, {"x": 7.7935, "y": 4.0104}, {"x": 7.793, "y": 4.305}, {"x": 4.6507, "y": 4.3002}]}], "spans": [{"offset": 254, "length": 52}]}, {"role": null, "content": "PROCESO DE MUESTREO DE LOS TANQUES DE ALMACENAMIENTO", "bounding_regions": [{"page_number": 1, "polygon": [{"x": 0.5874, "y": 7.0994}, {"x": 3.7251, "y": 7.1089}, {"x": 3.7242, "y": 7.403}, {"x": 0.5865, "y": 7.3934}]}], "spans": [{"offset": 307, "length": 52}]}, {"role": null, "content": "MEDICI\u00d3N DEL CORTE DE AGUA LIBRE EN LOS TANQUES DE ALMACENAMIENTO", "bounding_regions": [{"page_number": 1, "polygon": [{"x": 4.6511, "y": 7.066}, {"x": 7.7651, "y": 7.0755}, {"x": 7.7641, "y": 7.3892}, {"x": 4.6502, "y": 7.3797}]}], "spans": [{"offset": 360, "length": 65}]}, {"role": null, "content": "--", "bounding_regions": [{"page_number": 1, "polygon": [{"x": 7.7422, "y": 8.8184}, {"x": 7.8553, "y": 8.8086}, {"x": 7.8586, "y": 8.8465}, {"x": 7.7455, "y": 8.8563}]}], "spans": [{"offset": 426, "length": 2}]}, {"role": null, "content": "MEDICI\u00d3N DEL CORTE DE AGUA LIBRE EN LOS TANQUES DE ALMACENAMIENTO", "bounding_regions": [{"page_number": 1, "polygon": [{"x": 0.6447, "y": 10.2027}, {"x": 3.7637, "y": 10.217}, {"x": 3.7623, "y": 10.5294}, {"x": 0.6432, "y": 10.5151}]}], "spans": [{"offset": 429, "length": 65}]}, {"role": null, "content": "MUESTRAS TOMADAS DURANTE DE LA INSPECCI\u00d3N", "bounding_regions": [{"page_number": 1, "polygon": [{"x": 5.0522, "y": 10.2218}, {"x": 7.6452, "y": 10.2218}, {"x": 7.6452, "y": 10.513}, {"x": 5.0522, "y": 10.513}]}], "spans": [{"offset": 495, "length": 41}]}], "tables": [], "key_value_pairs": [{"key": {"content": "Ref. AIVEPET:", "bounding_regions": [{"page_number": 1, "polygon": [{"x": 3.2854, "y": 0.6889}, {"x": 4.3169, "y": 0.6923}, {"x": 4.3164, "y": 0.8498}, {"x": 3.2849, "y": 0.8464}]}], "spans": [{"offset": 53, "length": 13}]}, "value": {"content": "2023 02 077", "bounding_regions": [{"page_number": 1, "polygon": [{"x": 4.3407, "y": 0.6923}, {"x": 5.1621, "y": 0.6925}, {"x": 5.1621, "y": 0.85}, {"x": 4.3407, "y": 0.8498}]}], "spans": [{"offset": 67, "length": 11}]}, "confidence": 0.892}, {"key": {"content": "Fecha de Inspecci\u00f3n:", "bounding_regions": [{"page_number": 1, "polygon": [{"x": 3.0753, "y": 0.8785}, {"x": 4.6034, "y": 0.8785}, {"x": 4.6034, "y": 1.036}, {"x": 3.0753, "y": 1.036}]}], "spans": [{"offset": 79, "length": 20}]}, "value": {"content": "15/02/2023", "bounding_regions": [{"page_number": 1, "polygon": [{"x": 4.632, "y": 0.8785}, {"x": 5.3579, "y": 0.8832}, {"x": 5.3579, "y": 1.0265}, {"x": 4.632, "y": 1.0313}]}], "spans": [{"offset": 100, "length": 10}]}, "confidence": 0.906}], "styles": [], "documents": []}